aznews/__init__.py
aznews/py.typed
aznews-0.1.0.dist-info/WHEEL
aznews-0.1.0.dist-info/METADATA
aznews-0.1.0.dist-info/RECORD
