Metadata-Version: 2.3
Name: aznews
Version: 0.1.0
Summary: Python Crypto News Libs
Keywords: Crypto News,Python Crypto News Libs
Author: hhglory
Author-email: hhglory <hhglory@outlook.com>
Requires-Dist: loguru>=0.7.3
Requires-Python: >=3.12
